{"_id":"lodash._shimkeys","_rev":"27-5046a14cde5f6df719164e880ccbfbce","name":"lodash._shimkeys","description":"The internal Lo-Dash function `shimKeys` as a Node.js module generated by lodash-cli.","dist-tags":{"latest":"2.4.1"},"versions":{"2.0.0":{"name":"lodash._shimkeys","version":"2.0.0","description":"The internal Lo-Dash function `shimKeys` as a Node.js module generated by lodash-cli.","homepage":"http://lodash.com/custom-builds","license":"MIT","keywords":["customize","functional","lodash","performance","speed","util"],"author":{"name":"John-David Dalton","email":"john.david.dalton@gmail.com","url":"http://allyoucanleet.com/"},"contributors":[{"name":"John-David Dalton","email":"john.david.dalton@gmail.com","url":"http://allyoucanleet.com/"},{"name":"Blaine Bublitz","email":"blaine@iceddev.com","url":"http://iceddev.com/"},{"name":"Kit Cambridge","email":"github@kitcambridge.be","url":"http://kitcambridge.be/"},{"name":"Mathias Bynens","email":"mathias@qiwi.be","url":"http://mathiasbynens.be/"}],"bugs":{"url":"https://github.com/lodash/lodash-cli/issues"},"repository":{"type":"git","url":"https://github.com/lodash/lodash-cli.git"},"dependencies":{"lodash._objecttypes":"~2.0.0"},"_id":"lodash._shimkeys@2.0.0","dist":{"shasum":"7b3680609a38fe83ec7957c9159d64bdc8b8d79d","tarball":"http://registry.npmjs.org/lodash._shimkeys/-/lodash._shimkeys-2.0.0.tgz"},"_from":".","_npmVersion":"1.3.8","_npmUser":{"name":"jdalton","email":"john.david.dalton@gmail.com"},"maintainers":[{"name":"jdalton","email":"john.david.dalton@gmail.com"},{"name":"kitcambridge","email":"github@kitcambridge.be"},{"name":"mathias","email":"mathias@qiwi.be"},{"name":"phated","email":"blaine@iceddev.com"}],"directories":{}},"2.1.0":{"name":"lodash._shimkeys","version":"2.1.0","description":"The internal Lo-Dash function `shimKeys` as a Node.js module generated by lodash-cli.","homepage":"http://lodash.com/custom-builds","license":"MIT","keywords":["functional","lodash","lodash-modularized","performance","speed","util"],"author":{"name":"John-David Dalton","email":"john.david.dalton@gmail.com","url":"http://allyoucanleet.com/"},"contributors":[{"name":"John-David Dalton","email":"john.david.dalton@gmail.com","url":"http://allyoucanleet.com/"},{"name":"Blaine Bublitz","email":"blaine@iceddev.com","url":"http://iceddev.com/"},{"name":"Kit Cambridge","email":"github@kitcambridge.be","url":"http://kitcambridge.be/"},{"name":"Mathias Bynens","email":"mathias@qiwi.be","url":"http://mathiasbynens.be/"}],"bugs":{"url":"https://github.com/lodash/lodash-cli/issues"},"repository":{"type":"git","url":"https://github.com/lodash/lodash-cli.git"},"dependencies":{"lodash._objecttypes":"~2.1.0"},"_id":"lodash._shimkeys@2.1.0","dist":{"shasum":"2d136654cacfc9eb04ea6b11a117e74ceaac2110","tarball":"http://registry.npmjs.org/lodash._shimkeys/-/lodash._shimkeys-2.1.0.tgz"},"_from":".","_npmVersion":"1.3.8","_npmUser":{"name":"jdalton","email":"john.david.dalton@gmail.com"},"maintainers":[{"name":"jdalton","email":"john.david.dalton@gmail.com"},{"name":"kitcambridge","email":"github@kitcambridge.be"},{"name":"mathias","email":"mathias@qiwi.be"},{"name":"phated","email":"blaine@iceddev.com"}],"directories":{}},"2.2.0":{"name":"lodash._shimkeys","version":"2.2.0","description":"The internal Lo-Dash function `shimKeys` as a Node.js module generated by lodash-cli.","homepage":"http://lodash.com/custom-builds","license":"MIT","author":{"name":"John-David Dalton","email":"john.david.dalton@gmail.com","url":"http://allyoucanleet.com/"},"contributors":[{"name":"John-David Dalton","email":"john.david.dalton@gmail.com","url":"http://allyoucanleet.com/"},{"name":"Blaine Bublitz","email":"blaine@iceddev.com","url":"http://iceddev.com/"},{"name":"Kit Cambridge","email":"github@kitcambridge.be","url":"http://kitcambridge.be/"},{"name":"Mathias Bynens","email":"mathias@qiwi.be","url":"http://mathiasbynens.be/"}],"bugs":{"url":"https://github.com/lodash/lodash-cli/issues"},"repository":{"type":"git","url":"https://github.com/lodash/lodash-cli.git"},"dependencies":{"lodash._objecttypes":"~2.2.0"},"_id":"lodash._shimkeys@2.2.0","dist":{"shasum":"fa2920e47d03c8ceec3a1c6837d0ca9c73252166","tarball":"http://registry.npmjs.org/lodash._shimkeys/-/lodash._shimkeys-2.2.0.tgz"},"_from":".","_npmVersion":"1.3.8","_npmUser":{"name":"jdalton","email":"john.david.dalton@gmail.com"},"maintainers":[{"name":"jdalton","email":"john.david.dalton@gmail.com"},{"name":"kitcambridge","email":"github@kitcambridge.be"},{"name":"mathias","email":"mathias@qiwi.be"},{"name":"phated","email":"blaine@iceddev.com"}],"directories":{}},"2.2.1":{"name":"lodash._shimkeys","version":"2.2.1","description":"The internal Lo-Dash function `shimKeys` as a Node.js module generated by lodash-cli.","homepage":"http://lodash.com/custom-builds","license":"MIT","author":{"name":"John-David Dalton","email":"john.david.dalton@gmail.com","url":"http://allyoucanleet.com/"},"contributors":[{"name":"John-David Dalton","email":"john.david.dalton@gmail.com","url":"http://allyoucanleet.com/"},{"name":"Blaine Bublitz","email":"blaine@iceddev.com","url":"http://iceddev.com/"},{"name":"Kit Cambridge","email":"github@kitcambridge.be","url":"http://kitcambridge.be/"},{"name":"Mathias Bynens","email":"mathias@qiwi.be","url":"http://mathiasbynens.be/"}],"bugs":{"url":"https://github.com/lodash/lodash-cli/issues"},"repository":{"type":"git","url":"https://github.com/lodash/lodash-cli.git"},"dependencies":{"lodash._objecttypes":"~2.2.1"},"_id":"lodash._shimkeys@2.2.1","dist":{"shasum":"ed4e4b5d61214b2685400b185a59fabf59343455","tarball":"http://registry.npmjs.org/lodash._shimkeys/-/lodash._shimkeys-2.2.1.tgz"},"_from":".","_npmVersion":"1.3.11","_npmUser":{"name":"jdalton","email":"john.david.dalton@gmail.com"},"maintainers":[{"name":"jdalton","email":"john.david.dalton@gmail.com"},{"name":"kitcambridge","email":"github@kitcambridge.be"},{"name":"mathias","email":"mathias@qiwi.be"},{"name":"phated","email":"blaine@iceddev.com"}],"directories":{}},"2.3.0":{"name":"lodash._shimkeys","version":"2.3.0","description":"The internal Lo-Dash function `shimKeys` as a Node.js module generated by lodash-cli.","homepage":"http://lodash.com/custom-builds","license":"MIT","author":{"name":"John-David Dalton","email":"john.david.dalton@gmail.com","url":"http://allyoucanleet.com/"},"contributors":[{"name":"John-David Dalton","email":"john.david.dalton@gmail.com","url":"http://allyoucanleet.com/"},{"name":"Blaine Bublitz","email":"blaine@iceddev.com","url":"http://www.iceddev.com/"},{"name":"Kit Cambridge","email":"github@kitcambridge.be","url":"http://kitcambridge.be/"},{"name":"Mathias Bynens","email":"mathias@qiwi.be","url":"http://mathiasbynens.be/"}],"bugs":{"url":"https://github.com/lodash/lodash-cli/issues"},"repository":{"type":"git","url":"https://github.com/lodash/lodash-cli.git"},"dependencies":{"lodash._objecttypes":"~2.3.0"},"_id":"lodash._shimkeys@2.3.0","dist":{"shasum":"611f93149e3e6c721096b48769ef29537ada8ba9","tarball":"http://registry.npmjs.org/lodash._shimkeys/-/lodash._shimkeys-2.3.0.tgz"},"_from":".","_npmVersion":"1.3.11","_npmUser":{"name":"jdalton","email":"john.david.dalton@gmail.com"},"maintainers":[{"name":"jdalton","email":"john.david.dalton@gmail.com"},{"name":"kitcambridge","email":"github@kitcambridge.be"},{"name":"mathias","email":"mathias@qiwi.be"},{"name":"phated","email":"blaine@iceddev.com"}],"directories":{}},"2.4.0":{"name":"lodash._shimkeys","version":"2.4.0","description":"The internal Lo-Dash function `shimKeys` as a Node.js module generated by lodash-cli.","homepage":"http://lodash.com/custom-builds","license":"MIT","author":{"name":"John-David Dalton","email":"john.david.dalton@gmail.com","url":"http://allyoucanleet.com/"},"contributors":[{"name":"John-David Dalton","email":"john.david.dalton@gmail.com","url":"http://allyoucanleet.com/"},{"name":"Blaine Bublitz","email":"blaine@iceddev.com","url":"http://www.iceddev.com/"},{"name":"Kit Cambridge","email":"github@kitcambridge.be","url":"http://kitcambridge.be/"},{"name":"Mathias Bynens","email":"mathias@qiwi.be","url":"http://mathiasbynens.be/"}],"bugs":{"url":"https://github.com/lodash/lodash-cli/issues"},"repository":{"type":"git","url":"https://github.com/lodash/lodash-cli.git"},"dependencies":{"lodash._objecttypes":"~2.4.0"},"_id":"lodash._shimkeys@2.4.0","dist":{"shasum":"0c3c99b9256a0d02bf7e139f5a109dd1bdf68e22","tarball":"http://registry.npmjs.org/lodash._shimkeys/-/lodash._shimkeys-2.4.0.tgz"},"_from":".","_npmVersion":"1.3.14","_npmUser":{"name":"jdalton","email":"john.david.dalton@gmail.com"},"maintainers":[{"name":"jdalton","email":"john.david.dalton@gmail.com"},{"name":"kitcambridge","email":"github@kitcambridge.be"},{"name":"mathias","email":"mathias@qiwi.be"},{"name":"phated","email":"blaine@iceddev.com"}],"directories":{}},"2.4.1":{"name":"lodash._shimkeys","version":"2.4.1","description":"The internal Lo-Dash function `shimKeys` as a Node.js module generated by lodash-cli.","homepage":"http://lodash.com/custom-builds","license":"MIT","author":{"name":"John-David Dalton","email":"john.david.dalton@gmail.com","url":"http://allyoucanleet.com/"},"contributors":[{"name":"John-David Dalton","email":"john.david.dalton@gmail.com","url":"http://allyoucanleet.com/"},{"name":"Blaine Bublitz","email":"blaine@iceddev.com","url":"http://www.iceddev.com/"},{"name":"Kit Cambridge","email":"github@kitcambridge.be","url":"http://kitcambridge.be/"},{"name":"Mathias Bynens","email":"mathias@qiwi.be","url":"http://mathiasbynens.be/"}],"bugs":{"url":"https://github.com/lodash/lodash-cli/issues"},"repository":{"type":"git","url":"https://github.com/lodash/lodash-cli.git"},"dependencies":{"lodash._objecttypes":"~2.4.1"},"_id":"lodash._shimkeys@2.4.1","dist":{"shasum":"6e9cc9666ff081f0b5a6c978b83e242e6949d203","tarball":"http://registry.npmjs.org/lodash._shimkeys/-/lodash._shimkeys-2.4.1.tgz"},"_from":".","_npmVersion":"1.3.14","_npmUser":{"name":"jdalton","email":"john.david.dalton@gmail.com"},"maintainers":[{"name":"jdalton","email":"john.david.dalton@gmail.com"},{"name":"kitcambridge","email":"github@kitcambridge.be"},{"name":"mathias","email":"mathias@qiwi.be"},{"name":"phated","email":"blaine@iceddev.com"}],"directories":{}}},"readme":"# lodash._shimkeys v2.4.1\n\nThe internal [Lo-Dash](http://lodash.com/) function `shimKeys` as a [Node.js](http://nodejs.org/) module generated by [lodash-cli](https://npmjs.org/package/lodash-cli).\n\n## Author\n\n| [![twitter/jdalton](http://gravatar.com/avatar/299a3d891ff1920b69c364d061007043?s=70)](https://twitter.com/jdalton \"Follow @jdalton on Twitter\") |\n|---|\n| [John-David Dalton](http://allyoucanleet.com/) |\n\n## Contributors\n\n| [![twitter/blainebublitz](http://gravatar.com/avatar/ac1c67fd906c9fecd823ce302283b4c1?s=70)](https://twitter.com/blainebublitz \"Follow @BlaineBublitz on Twitter\") | [![twitter/kitcambridge](http://gravatar.com/avatar/6662a1d02f351b5ef2f8b4d815804661?s=70)](https://twitter.com/kitcambridge \"Follow @kitcambridge on Twitter\") | [![twitter/mathias](http://gravatar.com/avatar/24e08a9ea84deb17ae121074d0f17125?s=70)](https://twitter.com/mathias \"Follow @mathias on Twitter\") |\n|---|---|---|\n| [Blaine Bublitz](http://www.iceddev.com/) | [Kit Cambridge](http://kitcambridge.be/) | [Mathias Bynens](http://mathiasbynens.be/) |\n","maintainers":[{"name":"jdalton","email":"john.david.dalton@gmail.com"},{"name":"mathias","email":"mathias@qiwi.be"},{"name":"phated","email":"blaine@iceddev.com"}],"time":{"modified":"2015-09-27T18:39:11.645Z","created":"2013-09-23T06:29:22.682Z","2.0.0":"2013-09-23T07:30:44.203Z","2.1.0":"2013-09-23T07:50:07.772Z","2.2.0":"2013-09-29T22:07:14.993Z","2.2.1":"2013-10-03T18:48:05.615Z","2.3.0":"2013-11-11T16:45:12.341Z","2.4.0":"2013-11-26T19:54:21.144Z","2.4.1":"2013-12-03T17:10:00.106Z"},"author":{"name":"John-David Dalton","email":"john.david.dalton@gmail.com","url":"http://allyoucanleet.com/"},"repository":{"type":"git","url":"https://github.com/lodash/lodash-cli.git"},"homepage":"http://lodash.com/custom-builds","contributors":[{"name":"John-David Dalton","email":"john.david.dalton@gmail.com","url":"http://allyoucanleet.com/"},{"name":"Blaine Bublitz","email":"blaine@iceddev.com","url":"http://www.iceddev.com/"},{"name":"Kit Cambridge","email":"github@kitcambridge.be","url":"http://kitcambridge.be/"},{"name":"Mathias Bynens","email":"mathias@qiwi.be","url":"http://mathiasbynens.be/"}],"bugs":{"url":"https://github.com/lodash/lodash-cli/issues"},"license":"MIT","readmeFilename":"README.md","_attachments":{},"_etag":"\"6ZC9SHNLL9FXRZVO3D9ZTUCM2\""}