{"_id":"spdx-expression-parse","_rev":"1-12fb2b70f57899631aafb9d6793a5a1f","name":"spdx-expression-parse","description":"parse SPDX license expressions","dist-tags":{"latest":"1.0.0"},"versions":{"1.0.0":{"name":"spdx-expression-parse","description":"parse SPDX license expressions","version":"1.0.0","author":{"name":"Kyle E. Mitchell","email":"kyle@kemitchell.com","url":"http://kemitchell.com"},"dependencies":{"spdx-exceptions":"^1.0.0","spdx-license-ids":"^1.0.0"},"devDependencies":{"defence-cli":"^1.0.1","jison":"^0.4.15"},"keywords":["SPDX","law","legal","license","metadata","package","package.json","standards"],"license":"(MIT AND CC-BY-3.0)","repository":{"type":"git","url":"git+https://github.com/kemitchell/spdx-expression-parse.js.git"},"scripts":{"generate":"node generate-parser.js > parser.generated.js","prepublish":"npm run generate","pretest":"npm run generate","test":"defence -i javascript README.md | node"},"gitHead":"213bc03808f709a4ceaadb8466740a8c96c1e896","bugs":{"url":"https://github.com/kemitchell/spdx-expression-parse.js/issues"},"homepage":"https://github.com/kemitchell/spdx-expression-parse.js#readme","_id":"spdx-expression-parse@1.0.0","_shasum":"4fbb7e738c9e98fa0b0914dfd961ac6629fbcdef","_from":".","_npmVersion":"2.13.3","_nodeVersion":"0.12.7","_npmUser":{"name":"kemitchell","email":"kyle@kemitchell.com"},"dist":{"shasum":"4fbb7e738c9e98fa0b0914dfd961ac6629fbcdef","tarball":"http://registry.npmjs.org/spdx-expression-parse/-/spdx-expression-parse-1.0.0.tgz"},"maintainers":[{"name":"kemitchell","email":"kyle@kemitchell.com"}],"directories":{}}},"readme":"```javascript\nvar parse = require('./')\nvar assert = require('assert')\n\nvar firstAST = {\n  left: { license: 'LGPL-2.1' },\n  conjunction: 'or',\n  right: {\n    left: { license: 'BSD-3-Clause' },\n    conjunction: 'and',\n    right: { license: 'MIT' } } }\n\nassert.deepEqual(\n  parse('(LGPL-2.1 OR BSD-3-Clause AND MIT)'),\n  firstAST)\n\nvar secondAST = {\n  left: { license: 'MIT' },\n  conjunction: 'and',\n  right: {\n    left: {\n\t  license: 'LGPL-2.1',\n\t  plus: true },\n    conjunction: 'and',\n    right: { license: 'BSD-3-Clause' } } }\n\nassert.deepEqual(\n  parse('(MIT AND (LGPL-2.1+ AND BSD-3-Clause))'),\n  secondAST)\n```\n\n---\n\n[The Software Package Data Exchange (SPDX) specification](http://spdx.org) is the work of the [Linux Foundation](http://www.linuxfoundation.org) and its contributors, and is licensed under the terms of [the Creative Commons Attribution License 3.0 Unported (SPDX: \"CC-BY-3.0\")](http://spdx.org/licenses/CC-BY-3.0). \"SPDX\" is a United States federally registered trademark of the Linux Foundation.\n","maintainers":[{"name":"kemitchell","email":"kyle@kemitchell.com"}],"time":{"modified":"2015-08-02T03:24:08.717Z","created":"2015-08-02T03:24:08.717Z","1.0.0":"2015-08-02T03:24:08.717Z"},"homepage":"https://github.com/kemitchell/spdx-expression-parse.js#readme","keywords":["SPDX","law","legal","license","metadata","package","package.json","standards"],"repository":{"type":"git","url":"git+https://github.com/kemitchell/spdx-expression-parse.js.git"},"author":{"name":"Kyle E. Mitchell","email":"kyle@kemitchell.com","url":"http://kemitchell.com"},"bugs":{"url":"https://github.com/kemitchell/spdx-expression-parse.js/issues"},"license":"(MIT AND CC-BY-3.0)","readmeFilename":"README.md","_attachments":{},"_etag":"\"7WJWCBEHPWWP9HMR11AXWRVD7\""}